{"name":"Kindlecg","tagline":"a kindle collections generator","body":"# KindleCG\r\n## Directory Tree to Kindle Collections generator\r\n\r\nA command line ruby script that will generate collections in your kindle based on the directory structure of your ebooks.\r\nThe library to understand the mobi format are a straight port/refactor of the python plugin for calibre.\r\n\r\n## Installation\r\n\r\n    $ gem install KindleCG\r\n\r\n## Usage\r\n\r\nAfter installing the gem you will have access to a command line tool **kindlecg**.\r\nJust run it and will generate collections based on the directory structure of your ebooks in your kindle device.\r\n\r\n_*WARNING* The script is under development. It override your current collections!!!_\r\n\r\n## Contributing\r\n\r\n1. Fork it\r\n2. Create your feature branch (`git checkout -b my-new-feature`)\r\n3. Commit your changes (`git commit -am 'Add some feature'`)\r\n4. Push to the branch (`git push origin my-new-feature`)\r\n5. Create new Pull Request\r\n","google":"UA-42305685-1","note":"Don't delete this file! It's used internally to help with page regeneration."}